Metadata-Version: 1.1
Name: osf-aiohttpretty
Version: 0.1.0.2
Summary: AioHTTPretty
Home-page: https://github.com/CenterForOpenScience/aiohttpretty
Author: Center for Open Science
Author-email: contact@cos.io
License: UNKNOWN
Platform: UNKNOWN
Classifier: Development Status :: 4 - Beta
Classifier: Intended Audience :: Developers
Classifier: Natural Language :: English
Classifier: Programming Language :: Python :: 3
Classifier: Programming Language :: Python :: 3.4
Classifier: Programming Language :: Python :: 3.5
Classifier: Programming Language :: Python :: 3.6
